rag_cli/__init__.py
rag_cli/cli.py
rag_cli/embedder.py
rag_cli/main.py
rag_cli/rag.py
rag_cli/vector_store.py
rag_cli-0.3.1.dist-info/LICENSE
rag_cli-0.3.1.dist-info/METADATA
rag_cli-0.3.1.dist-info/WHEEL
rag_cli-0.3.1.dist-info/entry_points.txt
rag_cli-0.3.1.dist-info/RECORD
