Metadata-Version: 2.1
Name: rag-cli
Version: 0.3.1
Summary: A project to show good CLI practices with a fully fledged RAG system.
License: GNU GPL v3
Keywords: CLI,RAG,LLM,vector database,ollama
Author: Oliver Kenyon Wilkins
Author-email: okwilkins@googlemail.com
Requires-Python: >=3.9,<4.0
Classifier: License :: OSI Approved :: GNU Affero General Public License v3
Classifier: License :: Other/Proprietary License
Classifier: Programming Language :: Python :: 3
Classifier: Programming Language :: Python :: 3.9
Classifier: Programming Language :: Python :: 3.10
Classifier: Programming Language :: Python :: 3.11
Classifier: Programming Language :: Python :: 3.12
Requires-Dist: ollama (>=0.1.0)
Requires-Dist: qdrant-client (>=1.9.0)
